gitdual/__init__.py
gitdual/gitdual.py
gitdual-0.0.1.dist-info/licenses/AUTHORS.rst
gitdual-0.0.1.dist-info/licenses/LICENSE
gitdual-0.0.1.dist-info/METADATA
gitdual-0.0.1.dist-info/WHEEL
gitdual-0.0.1.dist-info/top_level.txt
gitdual-0.0.1.dist-info/RECORD
